{"type":"object","properties":{"json.trace.server":{"default":"off","scope":"window","type":"string","enum":["off","messages","verbose"],"description":"%json.tracing.desc%"},"json.schemaDownload.enable":{"tags":["usesOnlineServices"],"default":true,"description":"%json.enableSchemaDownload.desc%","type":"boolean"},"json.validate.enable":{"description":"%json.validate.enable.desc%","default":true,"scope":"window","type":"boolean"},"json.maxItemsComputed":{"default":5000,"description":"%json.maxItemsComputed.desc%","type":"number"},"json.schemas":{"items":{"default":{"fileMatch":["\/myfile"],"url":"schemaURL"},"properties":{"url":{"default":"\/user.schema.json","description":"%json.schemas.url.desc%","type":"string"},"fileMatch":{"items":{"default":"MyFile.json","description":"%json.schemas.fileMatch.item.desc%","type":"string"},"minItems":1,"description":"%json.schemas.fileMatch.desc%","type":"array"},"schema":{"description":"%json.schemas.schema.desc%","$ref":"http:\/\/json-schema.org\/draft-07\/schema#"}},"type":"object"},"description":"%json.schemas.desc%","scope":"resource","type":"array"},"json.colorDecorators.enable":{"default":true,"scope":"window","description":"%json.colorDecorators.enable.desc%","deprecationMessage":"%json.colorDecorators.enable.deprecationMessage%","type":"boolean"},"json.format.keepLines":{"description":"%json.format.keepLines.desc%","default":false,"scope":"window","type":"boolean"},"json.format.enable":{"description":"%json.format.enable.desc%","default":true,"scope":"window","type":"boolean"}},"id":"json","order":20,"title":"JSON"}